README.md
setup.py
Pyql700/imrenderer.py
Pyql700/multextimg.py
Pyql700/pwned.py
Pyql700/sticker.py
Pyql700/version.py
Pyql700.egg-info/PKG-INFO
Pyql700.egg-info/SOURCES.txt
Pyql700.egg-info/dependency_links.txt
Pyql700.egg-info/requires.txt
Pyql700.egg-info/top_level.txt
Pyql700/data/czfr.txt
Pyql700/data/ql700cupswrapper-1.1.4-0.i386.___
Pyql700/data/ql700lpr-1.1.4-0.i386.___
Pyql700/data/ql700pdrv-2.1.4-0.armhf.deb
Pyql700/data/ql700pdrv-3.1.5-0.i386.deb
bin/pyql700