Metadata-Version: 2.1
Name: Pyql700
Version: 0.4.9
Summary: Automatically created environment for python package
Home-page: https://gitlab.com/jaromrax/pyql700
Author:  me 
Author-email: me@example.com
License: GPL2
Platform: UNKNOWN
